rcn_py/.DS_Store
rcn_py/__about__.py
rcn_py/__init__.py
rcn_py/data_storage.py
rcn_py/database.py
rcn_py/neo4j_rsd.py
rcn_py/neo4j_scopus.py
rcn_py/openalex.py
rcn_py/orcid.py
rcn_py/rsd_sqlite.py
rcn_py/scholar.py
rcn_py/scopus.py
rcn_py/topic_modeling.py
rcn_py/visual.py
rcn_py-0.1.0.dist-info/METADATA
rcn_py-0.1.0.dist-info/WHEEL
rcn_py-0.1.0.dist-info/licenses/LICENSE.txt
rcn_py-0.1.0.dist-info/RECORD
